skene_growth/__init__.py
skene_growth/config.py
skene_growth/analyzers/__init__.py
skene_growth/analyzers/docs.py
skene_growth/analyzers/growth_features.py
skene_growth/analyzers/manifest.py
skene_growth/analyzers/prompts.py
skene_growth/analyzers/tech_stack.py
skene_growth/cli/__init__.py
skene_growth/cli/main.py
skene_growth/codebase/__init__.py
skene_growth/codebase/explorer.py
skene_growth/codebase/filters.py
skene_growth/codebase/tree.py
skene_growth/docs/__init__.py
skene_growth/docs/generator.py
skene_growth/docs/pseo/__init__.py
skene_growth/docs/pseo/builder.py
skene_growth/docs/templates/analysis.md.j2
skene_growth/docs/templates/growth_template.md.j2
skene_growth/docs/templates/plg_lifecycle_template.md.j2
skene_growth/docs/templates/product_docs.md.j2
skene_growth/docs/templates/seo_page.md.j2
skene_growth/growth_loops/__init__.py
skene_growth/growth_loops/selector.py
skene_growth/llm/__init__.py
skene_growth/llm/base.py
skene_growth/llm/factory.py
skene_growth/llm/providers/__init__.py
skene_growth/llm/providers/anthropic.py
skene_growth/llm/providers/gemini.py
skene_growth/llm/providers/lmstudio.py
skene_growth/llm/providers/ollama.py
skene_growth/llm/providers/openai.py
skene_growth/manifest/__init__.py
skene_growth/manifest/schema.py
skene_growth/mcp/__init__.py
skene_growth/mcp/__main__.py
skene_growth/mcp/cache.py
skene_growth/mcp/server.py
skene_growth/mcp/tools.py
skene_growth/objectives/__init__.py
skene_growth/objectives/generator.py
skene_growth/planner/__init__.py
skene_growth/planner/loops.py
skene_growth/planner/planner.py
skene_growth/strategies/__init__.py
skene_growth/strategies/base.py
skene_growth/strategies/context.py
skene_growth/strategies/multi_step.py
skene_growth/strategies/steps/__init__.py
skene_growth/strategies/steps/analyze.py
skene_growth/strategies/steps/base.py
skene_growth/strategies/steps/generate.py
skene_growth/strategies/steps/read_files.py
skene_growth/strategies/steps/select_files.py
skene_growth-0.1.8.dist-info/METADATA
skene_growth-0.1.8.dist-info/WHEEL
skene_growth-0.1.8.dist-info/entry_points.txt
skene_growth-0.1.8.dist-info/licenses/LICENSE
skene_growth-0.1.8.dist-info/RECORD
