Metadata-Version: 2.4
Name: skene-growth
Version: 0.1.8
Summary: PLG analysis toolkit for codebases - analyze code, detect growth opportunities, generate documentation
Project-URL: Homepage, https://www.skene.ai
Project-URL: Documentation, https://github.com/SkeneTechnologies/skene-growth#readme
Project-URL: Repository, https://github.com/SkeneTechnologies/skene-growth
Author: Skene Technologies
License: MIT
License-File: LICENSE
Keywords: ai-tools,analysis,codebase,developer-tools,documentation,growth,llm,mcp,mcp-server,plg
Classifier: Development Status :: 3 - Alpha
Classifier: Intended Audience :: Developers
Classifier: License :: OSI Approved :: MIT License
Classifier: Programming Language :: Python :: 3
Classifier: Programming Language :: Python :: 3.11
Classifier: Programming Language :: Python :: 3.12
Classifier: Programming Language :: Python :: 3.13
Requires-Python: >=3.11
Requires-Dist: aiofiles>=24.0
Requires-Dist: anthropic>=0.40
Requires-Dist: google-genai>=1.0
Requires-Dist: httpx>=0.27
Requires-Dist: jinja2>=3.0
Requires-Dist: loguru>=0.7.0
Requires-Dist: openai>=1.0
Requires-Dist: pydantic>=2.0
Requires-Dist: rich>=13.0
Requires-Dist: typer>=0.12
Provides-Extra: dev
Requires-Dist: pytest-asyncio>=0.23; extra == 'dev'
Requires-Dist: pytest>=8.0; extra == 'dev'
Requires-Dist: ruff>=0.4; extra == 'dev'
Provides-Extra: mcp
Requires-Dist: mcp>=1.0.0; extra == 'mcp'
Requires-Dist: xxhash>=3.0; extra == 'mcp'
